{
  "racist_ambience": {
    "subtitle": "subtitles.racist_ambience",
    "sounds": [
      {
        "name": "rubiesandrabies:racist_ambience",
        "stream": false
      }
    ]
  },
  "life_is_roblox": {
    "subtitle": "subtitles.life_is_roblox",
    "sounds": [
      {
        "name": "rubiesandrabies:lifeisroblox",
        "stream": true
      }
    ]
  },
  "what_time_is_it": {
    "subtitle": "subtitles.what_time_is_it",
    "sounds": [
      {
        "name": "rubiesandrabies:wahttime_is_it",
        "stream": false
      }
    ]
  },
  "musthavebeenthewind": {
    "subtitle": "subtitles.musthavebeenthewind",
    "sounds": [
      {
        "name": "rubiesandrabies:mustabeenthewind",
        "stream": false
      }
    ]
  },
  "evilracism": {
    "subtitle": "subtitles.evilracism",
    "sounds": [
      {
        "name": "rubiesandrabies:evilracism",
        "stream": false
      }
    ]
  },
  "yeah": {
    "subtitle": "subtitles.yeah",
    "sounds": [
      {
        "name": "rubiesandrabies:yeah",
        "stream": false
      }
    ]
  },
  "jackitup": {
    "subtitle": "subtitles.jackitup",
    "sounds": [
      {
        "name": "rubiesandrabies:jackitup",
        "stream": false
      }
    ]
  },
  "smash_hit": {
    "subtitle": "subtitles.smash_hit",
    "sounds": [
      {
        "name": "rubiesandrabies:smashhit",
        "stream": false
      }
    ]
  },
  "glassshatter": {
    "sounds": [
      {
        "name": "rubiesandrabies:glass",
        "stream": false
      }
    ]
  },
  "thegrandscream": {
    "sounds": [
      {
        "name": "rubiesandrabies:screaming",
        "stream": false
      }
    ]
  },
  "ding": {
    "subtitle": "subtitles.ding",
    "sounds": [
      {
        "name": "rubiesandrabies:wha",
        "stream": false
      }
    ]
  },
  "impaled": {
    "sounds": [
      {
        "name": "rubiesandrabies:uaaaaaaaa",
        "stream": false
      }
    ]
  },
  "glassidle": {
    "sounds": [
      {
        "name": "rubiesandrabies:glassidle",
        "stream": false
      }
    ]
  },
  "glasshit": {
    "sounds": [
      {
        "name": "rubiesandrabies:wha",
        "stream": false
      },
      {
        "name": "rubiesandrabies:glass4",
        "stream": false
      },
      {
        "name": "rubiesandrabies:glass3",
        "stream": false
      },
      {
        "name": "rubiesandrabies:glass2",
        "stream": false
      }
    ]
  },
  "thegrandabyssambience": {
    "subtitle": "subtitles.thegrandabyssambience",
    "sounds": [
      {
        "name": "rubiesandrabies:thegrandabyss",
        "stream": false
      }
    ]
  },
  "cowambient": {
    "sounds": [
      {
        "name": "rubiesandrabies:cow3",
        "stream": false
      },
      {
        "name": "rubiesandrabies:cow2",
        "stream": false
      },
      {
        "name": "rubiesandrabies:cow1",
        "stream": false
      }
    ]
  },
  "johnevilthethird": {
    "sounds": [
      {
        "name": "rubiesandrabies:evil",
        "stream": false
      }
    ]
  },
  "areyoubeingintentionallydense": {
    "sounds": [
      {
        "name": "rubiesandrabies:bwahy",
        "stream": false
      }
    ]
  },
  "yah": {
    "sounds": [
      {
        "name": "rubiesandrabies:what",
        "stream": false
      }
    ]
  },
  "sdpicemeatball": {
    "sounds": [
      {
        "name": "rubiesandrabies:spicymeatball",
        "stream": false
      }
    ]
  },
  "whbag_pitchup": {
    "sounds": [
      {
        "name": "rubiesandrabies:voicy_watch_him_become_a_god1",
        "stream": false
      }
    ]
  },
  "watchhimbecomeagawd": {
    "sounds": [
      {
        "name": "rubiesandrabies:voicy_watch_him_become_a_god",
        "stream": false
      }
    ]
  },
  "whbag_pitchdown": {
    "sounds": [
      {
        "name": "rubiesandrabies:voicy_watch_him_become_a_god2",
        "stream": false
      }
    ]
  },
  "atthespeedoflight": {
    "subtitle": "subtitles.atthespeedoflight",
    "sounds": [
      {
        "name": "rubiesandrabies:at_the_speed_of_light",
        "stream": true
      }
    ]
  },
  "knightliving": {
    "sounds": [
      {
        "name": "rubiesandrabies:knightofblunderogg",
        "stream": false
      }
    ]
  },
  "goatisscream": {
    "sounds": [
      {
        "name": "rubiesandrabies:rahhh",
        "stream": false
      }
    ]
  },
  "knightarmor": {
    "sounds": [
      {
        "name": "rubiesandrabies:knightarmor",
        "stream": false
      }
    ]
  },
  "femboyhurt": {
    "sounds": [
      {
        "name": "rubiesandrabies:issac-hurt-1",
        "stream": false
      }
    ]
  },
  "ambient": {
    "sounds": [
      {
        "name": "rubiesandrabies:ambient",
        "stream": false
      }
    ]
  },
  "knighthit": {
    "sounds": [
      {
        "name": "rubiesandrabies:knighthit",
        "stream": false
      }
    ]
  },
  "holywars_punishmentdue": {
    "sounds": [
      {
        "name": "rubiesandrabies:holy_wars_the_punishment_due_2004_remix",
        "stream": false
      }
    ]
  },
  "questionmark": {
    "sounds": [
      {
        "name": "rubiesandrabies:questionmark",
        "stream": false
      }
    ]
  },
  "knightdeath": {
    "sounds": [
      {
        "name": "rubiesandrabies:knightdeath",
        "stream": false
      }
    ]
  },
  "davedeath": {
    "sounds": [
      {
        "name": "rubiesandrabies:dave-mustaine-scream-made-with-voicemod1",
        "stream": false
      }
    ]
  },
  "cacophony": {
    "sounds": [
      {
        "name": "rubiesandrabies:cacophony",
        "stream": false
      }
    ]
  },
  "davescream": {
    "sounds": [
      {
        "name": "rubiesandrabies:dave-mustaine-scream-made-with-voicemod",
        "stream": false
      }
    ]
  },
  "thunderlive": {
    "sounds": [
      {
        "name": "rubiesandrabies:thunderlive",
        "stream": false
      }
    ]
  },
  "thunderdeath": {
    "sounds": [
      {
        "name": "rubiesandrabies:thunderdeath",
        "stream": false
      }
    ]
  },
  "windland": {
    "sounds": [
      {
        "name": "rubiesandrabies:windland",
        "stream": true
      }
    ]
  },
  "windland_ambience": {
    "sounds": [
      {
        "name": "rubiesandrabies:windland_ambience",
        "stream": false
      }
    ]
  }
}